{
"type": "FeatureCollection",
"features": [
{ "type": "Feature", "properties": { "strassenschluessel": "05974000004808001", "bezeichnung": "Balksweg" }, "geometry": { "type": "Point", "coordinates": [ 8.077225703695868, 51.631312819459275 ] } },
{ "type": "Feature", "properties": { "strassenschluessel": "05974000004808002", "bezeichnung": "Gut Schweckhausen" }, "geometry": { "type": "Point", "coordinates": [ 8.07187608328895, 51.628082235533185 ] } },
{ "type": "Feature", "properties": { "strassenschluessel": "05974000004808003", "bezeichnung": "Hillingsen" }, "geometry": { "type": "Point", "coordinates": [ 8.082005754854643, 51.624864165780259 ] } },
{ "type": "Feature", "properties": { "strassenschluessel": "05974000004808008", "bezeichnung": "Aldehold" }, "geometry": { "type": "Point", "coordinates": [ 8.049473810335908, 51.615627080331734 ] } },
{ "type": "Feature", "properties": { "strassenschluessel": "05974000004808009", "bezeichnung": "Berwicker Straße" }, "geometry": { "type": "Point", "coordinates": [ 8.029114933198123, 51.619512644466397 ] } },
{ "type": "Feature", "properties": { "strassenschluessel": "05974000004808010", "bezeichnung": "Borghausen" }, "geometry": { "type": "Point", "coordinates": [ 8.041317091640451, 51.631133383568269 ] } },
{ "type": "Feature", "properties": { "strassenschluessel": "05974000004808011", "bezeichnung": "Buchenhecke" }, "geometry": { "type": "Point", "coordinates": [ 8.019555251701004, 51.620345638572516 ] } },
{ "type": "Feature", "properties": { "strassenschluessel": "05974000004808012", "bezeichnung": "Gerstenkamp" }, "geometry": { "type": "Point", "coordinates": [ 8.02384745099644, 51.616319060403463 ] } },
{ "type": "Feature", "properties": { "strassenschluessel": "05974000004808013", "bezeichnung": "Haus Nehlen" }, "geometry": { "type": "Point", "coordinates": [ 8.027492863123964, 51.625876327189303 ] } },
{ "type": "Feature", "properties": { "strassenschluessel": "05974000004808014", "bezeichnung": "Huer" }, "geometry": { "type": "Point", "coordinates": [ 8.045070225826324, 51.613288625066502 ] } },
{ "type": "Feature", "properties": { "strassenschluessel": "05974000004808015", "bezeichnung": "Hüttenstraße" }, "geometry": { "type": "Point", "coordinates": [ 8.029764626825804, 51.620195037784491 ] } },
{ "type": "Feature", "properties": { "strassenschluessel": "05974000004808016", "bezeichnung": "Kaiser Weg" }, "geometry": { "type": "Point", "coordinates": [ 8.033016607617451, 51.620743258730442 ] } },
{ "type": "Feature", "properties": { "strassenschluessel": "05974000004808017", "bezeichnung": "Kloster Straße" }, "geometry": { "type": "Point", "coordinates": [ 8.037444207360442, 51.61997307492134 ] } },
{ "type": "Feature", "properties": { "strassenschluessel": "05974000004808018", "bezeichnung": "Merschstraße" }, "geometry": { "type": "Point", "coordinates": [ 8.030195977964471, 51.62236913170517 ] } },
{ "type": "Feature", "properties": { "strassenschluessel": "05974000004808019", "bezeichnung": "Schmiedestraße" }, "geometry": { "type": "Point", "coordinates": [ 8.027352152335334, 51.620051897024915 ] } },
{ "type": "Feature", "properties": { "strassenschluessel": "05974000004808024", "bezeichnung": "Auf der Witteborg" }, "geometry": { "type": "Point", "coordinates": [ 8.069948621329436, 51.6123242795192 ] } },
{ "type": "Feature", "properties": { "strassenschluessel": "05974000004808025", "bezeichnung": "Blumrother Straße" }, "geometry": { "type": "Point", "coordinates": [ 8.064743497956623, 51.614804235918314 ] } },
{ "type": "Feature", "properties": { "strassenschluessel": "05974000004808026", "bezeichnung": "Heidstraße" }, "geometry": { "type": "Point", "coordinates": [ 8.06828902723489, 51.618274100259804 ] } },
{ "type": "Feature", "properties": { "strassenschluessel": "05974000004808027", "bezeichnung": "Jünglingshof" }, "geometry": { "type": "Point", "coordinates": [ 8.069548805905253, 51.604766795824737 ] } },
{ "type": "Feature", "properties": { "strassenschluessel": "05974000004808029", "bezeichnung": "Am Bahnhof" }, "geometry": { "type": "Point", "coordinates": [ 8.032891338345669, 51.597645002416662 ] } },
{ "type": "Feature", "properties": { "strassenschluessel": "05974000004808030", "bezeichnung": "Am Butterkamp" }, "geometry": { "type": "Point", "coordinates": [ 8.034951241587883, 51.602596762440704 ] } },
{ "type": "Feature", "properties": { "strassenschluessel": "05974000004808031", "bezeichnung": "Am Klei" }, "geometry": { "type": "Point", "coordinates": [ 8.028233330596949, 51.598975698045408 ] } },
{ "type": "Feature", "properties": { "strassenschluessel": "05974000004808032", "bezeichnung": "Am Kotten" }, "geometry": { "type": "Point", "coordinates": [ 8.025927085613857, 51.609219374087743 ] } },
{ "type": "Feature", "properties": { "strassenschluessel": "05974000004808033", "bezeichnung": "Am Kuckuck" }, "geometry": { "type": "Point", "coordinates": [ 8.047524099200471, 51.610427070896733 ] } },
{ "type": "Feature", "properties": { "strassenschluessel": "05974000004808034", "bezeichnung": "Asternstraße" }, "geometry": { "type": "Point", "coordinates": [ 8.0394010913781, 51.599361221718603 ] } },
{ "type": "Feature", "properties": { "strassenschluessel": "05974000004808035", "bezeichnung": "Diedrich-Düllmann-Straße" }, "geometry": { "type": "Point", "coordinates": [ 8.037282382626014, 51.599193025930958 ] } },
{ "type": "Feature", "properties": { "strassenschluessel": "05974000004808036", "bezeichnung": "Blumenstraße" }, "geometry": { "type": "Point", "coordinates": [ 8.039669128042341, 51.598913507024626 ] } },
{ "type": "Feature", "properties": { "strassenschluessel": "05974000004808037", "bezeichnung": "Bördestraße" }, "geometry": { "type": "Point", "coordinates": [ 8.043939922488256, 51.60377848864772 ] } },
{ "type": "Feature", "properties": { "strassenschluessel": "05974000004808038", "bezeichnung": "Borgelerlinde" }, "geometry": { "type": "Point", "coordinates": [ 8.051448043423134, 51.605723980698222 ] } },
{ "type": "Feature", "properties": { "strassenschluessel": "05974000004808039", "bezeichnung": "Dahlienweg" }, "geometry": { "type": "Point", "coordinates": [ 8.038326412437351, 51.600460822157132 ] } },
{ "type": "Feature", "properties": { "strassenschluessel": "05974000004808040", "bezeichnung": "Fahnener Weg" }, "geometry": { "type": "Point", "coordinates": [ 8.009606249981257, 51.611039132306153 ] } },
{ "type": "Feature", "properties": { "strassenschluessel": "05974000004808041", "bezeichnung": "Hammer Landstraße" }, "geometry": { "type": "Point", "coordinates": [ 8.040880269136712, 51.612232357124405 ] } },
{ "type": "Feature", "properties": { "strassenschluessel": "05974000004808042", "bezeichnung": "Haselhorst" }, "geometry": { "type": "Point", "coordinates": [ 8.041774934876836, 51.612044719902691 ] } },
{ "type": "Feature", "properties": { "strassenschluessel": "05974000004808043", "bezeichnung": "Hattropholser Straße" }, "geometry": { "type": "Point", "coordinates": [ 8.037055941057355, 51.600837668513336 ] } },
{ "type": "Feature", "properties": { "strassenschluessel": "05974000004808044", "bezeichnung": "Haus Broel" }, "geometry": { "type": "Point", "coordinates": [ 8.039167065667009, 51.593601607414229 ] } },
{ "type": "Feature", "properties": { "strassenschluessel": "05974000004808045", "bezeichnung": "Jahnstraße" }, "geometry": { "type": "Point", "coordinates": [ 8.041594168548398, 51.601492585547462 ] } },
{ "type": "Feature", "properties": { "strassenschluessel": "05974000004808046", "bezeichnung": "Kellerstraße" }, "geometry": { "type": "Point", "coordinates": [ 8.03532164874829, 51.600146917090363 ] } },
{ "type": "Feature", "properties": { "strassenschluessel": "05974000004808047", "bezeichnung": "Lohstraße" }, "geometry": { "type": "Point", "coordinates": [ 8.037416918384832, 51.601893189328813 ] } },
{ "type": "Feature", "properties": { "strassenschluessel": "05974000004808048", "bezeichnung": "Lütge Haselhorst" }, "geometry": { "type": "Point", "coordinates": [ 8.03725835020677, 51.611285029886055 ] } },
{ "type": "Feature", "properties": { "strassenschluessel": "05974000004808049", "bezeichnung": "Nelkenweg" }, "geometry": { "type": "Point", "coordinates": [ 8.04098752805124, 51.598997398414959 ] } },
{ "type": "Feature", "properties": { "strassenschluessel": "05974000004808050", "bezeichnung": "Osterbrei" }, "geometry": { "type": "Point", "coordinates": [ 8.040440683369937, 51.601022698129356 ] } },
{ "type": "Feature", "properties": { "strassenschluessel": "05974000004808051", "bezeichnung": "Oststraße" }, "geometry": { "type": "Point", "coordinates": [ 8.045821703953445, 51.603667158275698 ] } },
{ "type": "Feature", "properties": { "strassenschluessel": "05974000004808052", "bezeichnung": "Pfarrweg" }, "geometry": { "type": "Point", "coordinates": [ 8.036066584471383, 51.600459946911784 ] } },
{ "type": "Feature", "properties": { "strassenschluessel": "05974000004808053", "bezeichnung": "Rosenweg" }, "geometry": { "type": "Point", "coordinates": [ 8.039970700393692, 51.599836524667197 ] } },
{ "type": "Feature", "properties": { "strassenschluessel": "05974000004808054", "bezeichnung": "Tulpenweg" }, "geometry": { "type": "Point", "coordinates": [ 8.039034238306972, 51.600037086637073 ] } },
{ "type": "Feature", "properties": { "strassenschluessel": "05974000004808055", "bezeichnung": "Zum Hiltenkamp" }, "geometry": { "type": "Point", "coordinates": [ 8.015956246036533, 51.600249401326153 ] } },
{ "type": "Feature", "properties": { "strassenschluessel": "05974000004808056", "bezeichnung": "Uhlenburg" }, "geometry": { "type": "Point", "coordinates": [ 8.036423615800061, 51.593169709207466 ] } },
{ "type": "Feature", "properties": { "strassenschluessel": "05974000004808057", "bezeichnung": "Am Sandknapp" }, "geometry": { "type": "Point", "coordinates": [ 8.033063700511388, 51.599139827666541 ] } },
{ "type": "Feature", "properties": { "strassenschluessel": "05974000004808058", "bezeichnung": "Am Butterberge" }, "geometry": { "type": "Point", "coordinates": [ 8.03760971843597, 51.602777339063593 ] } },
{ "type": "Feature", "properties": { "strassenschluessel": "05974000004808059", "bezeichnung": "Zum Schulzenhof" }, "geometry": { "type": "Point", "coordinates": [ 8.033897307480341, 51.59982876937061 ] } },
{ "type": "Feature", "properties": { "strassenschluessel": "05974000004808076", "bezeichnung": "Ahseweg" }, "geometry": { "type": "Point", "coordinates": [ 7.959152732407809, 51.641402591283821 ] } },
{ "type": "Feature", "properties": { "strassenschluessel": "05974000004808077", "bezeichnung": "Am Freistuhl" }, "geometry": { "type": "Point", "coordinates": [ 7.954477152000185, 51.652261543028146 ] } },
{ "type": "Feature", "properties": { "strassenschluessel": "05974000004808078", "bezeichnung": "Dinker Berg" }, "geometry": { "type": "Point", "coordinates": [ 7.968496218917769, 51.649698876888245 ] } },
{ "type": "Feature", "properties": { "strassenschluessel": "05974000004808079", "bezeichnung": "Eichenallee" }, "geometry": { "type": "Point", "coordinates": [ 7.961203949522441, 51.651928781849293 ] } },
{ "type": "Feature", "properties": { "strassenschluessel": "05974000004808080", "bezeichnung": "Feldstraße" }, "geometry": { "type": "Point", "coordinates": [ 7.95970611829717, 51.645027558631064 ] } },
{ "type": "Feature", "properties": { "strassenschluessel": "05974000004808081", "bezeichnung": "Fliederweg" }, "geometry": { "type": "Point", "coordinates": [ 7.962163404232061, 51.64456382357578 ] } },
{ "type": "Feature", "properties": { "strassenschluessel": "05974000004808082", "bezeichnung": "Hellweg" }, "geometry": { "type": "Point", "coordinates": [ 7.95983745644524, 51.642570018839237 ] } },
{ "type": "Feature", "properties": { "strassenschluessel": "05974000004808083", "bezeichnung": "Kirchplatz" }, "geometry": { "type": "Point", "coordinates": [ 7.961910571890686, 51.641758857597992 ] } },
{ "type": "Feature", "properties": { "strassenschluessel": "05974000004808084", "bezeichnung": "Lippestraße" }, "geometry": { "type": "Point", "coordinates": [ 7.965565068932119, 51.650898608324603 ] } },
{ "type": "Feature", "properties": { "strassenschluessel": "05974000004808085", "bezeichnung": "Mühlenweg" }, "geometry": { "type": "Point", "coordinates": [ 7.951190330931087, 51.642116722107858 ] } },
{ "type": "Feature", "properties": { "strassenschluessel": "05974000004808086", "bezeichnung": "Oitrup" }, "geometry": { "type": "Point", "coordinates": [ 7.958450340138942, 51.647181249065824 ] } },
{ "type": "Feature", "properties": { "strassenschluessel": "05974000004808087", "bezeichnung": "Sängerhof" }, "geometry": { "type": "Point", "coordinates": [ 7.965051601866808, 51.645724534199665 ] } },
{ "type": "Feature", "properties": { "strassenschluessel": "05974000004808088", "bezeichnung": "Schwannemühle" }, "geometry": { "type": "Point", "coordinates": [ 7.950595256220389, 51.640689775231991 ] } },
{ "type": "Feature", "properties": { "strassenschluessel": "05974000004808089", "bezeichnung": "Wiesenstraße" }, "geometry": { "type": "Point", "coordinates": [ 7.962581660991462, 51.641588683134906 ] } },
{ "type": "Feature", "properties": { "strassenschluessel": "05974000004808090", "bezeichnung": "Winkelweg" }, "geometry": { "type": "Point", "coordinates": [ 7.957940780420882, 51.643340600682059 ] } },
{ "type": "Feature", "properties": { "strassenschluessel": "05974000004808091", "bezeichnung": "Flurstraße" }, "geometry": { "type": "Point", "coordinates": [ 7.958213038237243, 51.64477129926685 ] } },
{ "type": "Feature", "properties": { "strassenschluessel": "05974000004808096", "bezeichnung": "Goseländchen" }, "geometry": { "type": "Point", "coordinates": [ 7.973621529861173, 51.633113556539115 ] } },
{ "type": "Feature", "properties": { "strassenschluessel": "05974000004808097", "bezeichnung": "Hasselfeld" }, "geometry": { "type": "Point", "coordinates": [ 7.943233963731926, 51.632708449939742 ] } },
{ "type": "Feature", "properties": { "strassenschluessel": "05974000004808098", "bezeichnung": "Haus Galen" }, "geometry": { "type": "Point", "coordinates": [ 7.953441059754417, 51.635899017682696 ] } },
{ "type": "Feature", "properties": { "strassenschluessel": "05974000004808099", "bezeichnung": "Hauskamp" }, "geometry": { "type": "Point", "coordinates": [ 7.940668559403879, 51.629403306390628 ] } },
{ "type": "Feature", "properties": { "strassenschluessel": "05974000004808100", "bezeichnung": "Haus Matena" }, "geometry": { "type": "Point", "coordinates": [ 7.959835516836261, 51.63553603508791 ] } },
{ "type": "Feature", "properties": { "strassenschluessel": "05974000004808101", "bezeichnung": "Bernhard-Honkamp-Straße" }, "geometry": { "type": "Point", "coordinates": [ 7.960715759528564, 51.625710659211407 ] } },
{ "type": "Feature", "properties": { "strassenschluessel": "05974000004808102", "bezeichnung": "Kettlerholz" }, "geometry": { "type": "Point", "coordinates": [ 7.960013210873187, 51.63180669735673 ] } },
{ "type": "Feature", "properties": { "strassenschluessel": "05974000004808103", "bezeichnung": "Kortemühle" }, "geometry": { "type": "Point", "coordinates": [ 7.933358437394964, 51.6267257632718 ] } },
{ "type": "Feature", "properties": { "strassenschluessel": "05974000004808104", "bezeichnung": "Rauksloh" }, "geometry": { "type": "Point", "coordinates": [ 7.959504164477215, 51.631670276777278 ] } },
{ "type": "Feature", "properties": { "strassenschluessel": "05974000004808105", "bezeichnung": "Rübenkamp" }, "geometry": { "type": "Point", "coordinates": [ 7.952261818101543, 51.632795380596669 ] } },
{ "type": "Feature", "properties": { "strassenschluessel": "05974000004808106", "bezeichnung": "Schürenholz" }, "geometry": { "type": "Point", "coordinates": [ 7.955286851115841, 51.627257006670256 ] } },
{ "type": "Feature", "properties": { "strassenschluessel": "05974000004808116", "bezeichnung": "Holserweg" }, "geometry": { "type": "Point", "coordinates": [ 7.987359199276203, 51.58111920661365 ] } },
{ "type": "Feature", "properties": { "strassenschluessel": "05974000004808117", "bezeichnung": "Holzstraße" }, "geometry": { "type": "Point", "coordinates": [ 7.987245324171631, 51.584650924109084 ] } },
{ "type": "Feature", "properties": { "strassenschluessel": "05974000004808118", "bezeichnung": "In Ehningsen" }, "geometry": { "type": "Point", "coordinates": [ 7.981818054360224, 51.582578078856983 ] } },
{ "type": "Feature", "properties": { "strassenschluessel": "05974000004808119", "bezeichnung": "Kreuzweg" }, "geometry": { "type": "Point", "coordinates": [ 7.980236890706342, 51.583985875316415 ] } },
{ "type": "Feature", "properties": { "strassenschluessel": "05974000004808120", "bezeichnung": "Alte Kreisstraße" }, "geometry": { "type": "Point", "coordinates": [ 7.983484294245716, 51.582521153135723 ] } },
{ "type": "Feature", "properties": { "strassenschluessel": "05974000004808121", "bezeichnung": "Grüner Weg" }, "geometry": { "type": "Point", "coordinates": [ 7.980186806355811, 51.584566731876428 ] } },
{ "type": "Feature", "properties": { "strassenschluessel": "05974000004808124", "bezeichnung": "Am Birnbaum" }, "geometry": { "type": "Point", "coordinates": [ 8.005775138721503, 51.590621895338813 ] } },
{ "type": "Feature", "properties": { "strassenschluessel": "05974000004808125", "bezeichnung": "Am Hinkamp" }, "geometry": { "type": "Point", "coordinates": [ 7.999214440273937, 51.586496898950834 ] } },
{ "type": "Feature", "properties": { "strassenschluessel": "05974000004808126", "bezeichnung": "Auf der Höhe" }, "geometry": { "type": "Point", "coordinates": [ 7.997439788611583, 51.594685640265119 ] } },
{ "type": "Feature", "properties": { "strassenschluessel": "05974000004808127", "bezeichnung": "Einecker Straße" }, "geometry": { "type": "Point", "coordinates": [ 7.998197773950482, 51.593117370290727 ] } },
{ "type": "Feature", "properties": { "strassenschluessel": "05974000004808128", "bezeichnung": "Zur Einecker Vöhde" }, "geometry": { "type": "Point", "coordinates": [ 8.005449454475414, 51.602106164231827 ] } },
{ "type": "Feature", "properties": { "strassenschluessel": "05974000004808129", "bezeichnung": "Im Hufeisen" }, "geometry": { "type": "Point", "coordinates": [ 8.000352168674224, 51.590695741794427 ] } },
{ "type": "Feature", "properties": { "strassenschluessel": "05974000004808136", "bezeichnung": "Am Westbach" }, "geometry": { "type": "Point", "coordinates": [ 8.008483964530853, 51.584706334682636 ] } },
{ "type": "Feature", "properties": { "strassenschluessel": "05974000004808137", "bezeichnung": "Auf der Hofestatt" }, "geometry": { "type": "Point", "coordinates": [ 7.996622755593651, 51.581416614935733 ] } },
{ "type": "Feature", "properties": { "strassenschluessel": "05974000004808138", "bezeichnung": "Eineckerholser Straße" }, "geometry": { "type": "Point", "coordinates": [ 8.006074493160273, 51.584230128541655 ] } },
{ "type": "Feature", "properties": { "strassenschluessel": "05974000004808139", "bezeichnung": "In den Kämpen" }, "geometry": { "type": "Point", "coordinates": [ 8.008546044889352, 51.585165868752121 ] } },
{ "type": "Feature", "properties": { "strassenschluessel": "05974000004808140", "bezeichnung": "In der Heide" }, "geometry": { "type": "Point", "coordinates": [ 8.000979170959019, 51.58365283930128 ] } },
{ "type": "Feature", "properties": { "strassenschluessel": "05974000004808146", "bezeichnung": "Am Heidewald" }, "geometry": { "type": "Point", "coordinates": [ 7.958370237213051, 51.593179487803752 ] } },
{ "type": "Feature", "properties": { "strassenschluessel": "05974000004808147", "bezeichnung": "Flerker Landwehr" }, "geometry": { "type": "Point", "coordinates": [ 7.961232898982081, 51.589878879671446 ] } },
{ "type": "Feature", "properties": { "strassenschluessel": "05974000004808148", "bezeichnung": "Flerker Straße" }, "geometry": { "type": "Point", "coordinates": [ 7.952636325801174, 51.595077732798408 ] } },
{ "type": "Feature", "properties": { "strassenschluessel": "05974000004808149", "bezeichnung": "Fritz-Schulze-Straße" }, "geometry": { "type": "Point", "coordinates": [ 7.956503266366805, 51.59590491934523 ] } },
{ "type": "Feature", "properties": { "strassenschluessel": "05974000004808150", "bezeichnung": "Klotinger Heide" }, "geometry": { "type": "Point", "coordinates": [ 7.962339339608921, 51.601456190456801 ] } },
{ "type": "Feature", "properties": { "strassenschluessel": "05974000004808151", "bezeichnung": "Lohbrei Weg" }, "geometry": { "type": "Point", "coordinates": [ 7.957346414526891, 51.596935665134176 ] } },
{ "type": "Feature", "properties": { "strassenschluessel": "05974000004808152", "bezeichnung": "Pappelallee" }, "geometry": { "type": "Point", "coordinates": [ 7.951641253675842, 51.594101570304787 ] } },
{ "type": "Feature", "properties": { "strassenschluessel": "05974000004808153", "bezeichnung": "Stemmerk" }, "geometry": { "type": "Point", "coordinates": [ 7.940644978865558, 51.591861592248272 ] } },
{ "type": "Feature", "properties": { "strassenschluessel": "05974000004808154", "bezeichnung": "Twietenweg" }, "geometry": { "type": "Point", "coordinates": [ 7.95185714281494, 51.594777667844546 ] } },
{ "type": "Feature", "properties": { "strassenschluessel": "05974000004808155", "bezeichnung": "Uferstraße" }, "geometry": { "type": "Point", "coordinates": [ 7.950154439453425, 51.596868080631687 ] } },
{ "type": "Feature", "properties": { "strassenschluessel": "05974000004808156", "bezeichnung": "von-Papen-Weg" }, "geometry": { "type": "Point", "coordinates": [ 7.955087208205027, 51.591338290582122 ] } },
{ "type": "Feature", "properties": { "strassenschluessel": "05974000004808166", "bezeichnung": "Am Graben" }, "geometry": { "type": "Point", "coordinates": [ 7.92419468038844, 51.618273050212018 ] } },
{ "type": "Feature", "properties": { "strassenschluessel": "05974000004808167", "bezeichnung": "Auf'm Eeka" }, "geometry": { "type": "Point", "coordinates": [ 7.926974303038477, 51.620866225479226 ] } },
{ "type": "Feature", "properties": { "strassenschluessel": "05974000004808168", "bezeichnung": "Bewerstraße" }, "geometry": { "type": "Point", "coordinates": [ 7.918648760104925, 51.618539090509977 ] } },
{ "type": "Feature", "properties": { "strassenschluessel": "05974000004808169", "bezeichnung": "Birkenbusch" }, "geometry": { "type": "Point", "coordinates": [ 7.927403904605361, 51.617658485997048 ] } },
{ "type": "Feature", "properties": { "strassenschluessel": "05974000004808170", "bezeichnung": "Dreihausen" }, "geometry": { "type": "Point", "coordinates": [ 7.919228349378535, 51.609808456978683 ] } },
{ "type": "Feature", "properties": { "strassenschluessel": "05974000004808171", "bezeichnung": "Gerwins Hof" }, "geometry": { "type": "Point", "coordinates": [ 7.921646159334507, 51.620761486231949 ] } },
{ "type": "Feature", "properties": { "strassenschluessel": "05974000004808172", "bezeichnung": "Illinger Straße" }, "geometry": { "type": "Point", "coordinates": [ 7.924815192730908, 51.617760153425159 ] } },
{ "type": "Feature", "properties": { "strassenschluessel": "05974000004808173", "bezeichnung": "Massbrauck" }, "geometry": { "type": "Point", "coordinates": [ 7.917879554663681, 51.615777042698333 ] } },
{ "type": "Feature", "properties": { "strassenschluessel": "05974000004808174", "bezeichnung": "Osterfeld" }, "geometry": { "type": "Point", "coordinates": [ 7.92904248003089, 51.625050758848559 ] } },
{ "type": "Feature", "properties": { "strassenschluessel": "05974000004808175", "bezeichnung": "Salzbachweg" }, "geometry": { "type": "Point", "coordinates": [ 7.92724149320607, 51.616452850844446 ] } },
{ "type": "Feature", "properties": { "strassenschluessel": "05974000004808176", "bezeichnung": "Aufm Kreuzkamp" }, "geometry": { "type": "Point", "coordinates": [ 7.914938914742208, 51.613028495970219 ] } },
{ "type": "Feature", "properties": { "strassenschluessel": "05974000004808177", "bezeichnung": "Kampstraße" }, "geometry": null },
{ "type": "Feature", "properties": { "strassenschluessel": "05974000004808178", "bezeichnung": "Auf dem Kamp" }, "geometry": null },
{ "type": "Feature", "properties": { "strassenschluessel": "05974000004808181", "bezeichnung": "Am Knapp" }, "geometry": { "type": "Point", "coordinates": [ 7.970516553363252, 51.61038317512493 ] } },
{ "type": "Feature", "properties": { "strassenschluessel": "05974000004808182", "bezeichnung": "Breite Straße" }, "geometry": { "type": "Point", "coordinates": [ 7.986905411629305, 51.605538055282125 ] } },
{ "type": "Feature", "properties": { "strassenschluessel": "05974000004808183", "bezeichnung": "Hohe Brücke" }, "geometry": { "type": "Point", "coordinates": [ 7.992694279257613, 51.609561175971649 ] } },
{ "type": "Feature", "properties": { "strassenschluessel": "05974000004808184", "bezeichnung": "Im Erlei" }, "geometry": { "type": "Point", "coordinates": [ 7.982884250071945, 51.614411827227727 ] } },
{ "type": "Feature", "properties": { "strassenschluessel": "05974000004808185", "bezeichnung": "Klotinger Straße" }, "geometry": { "type": "Point", "coordinates": [ 7.981606971601316, 51.602766011622357 ] } },
{ "type": "Feature", "properties": { "strassenschluessel": "05974000004808186", "bezeichnung": "Zur Bonnekoh" }, "geometry": { "type": "Point", "coordinates": [ 7.978030739774699, 51.60037107855451 ] } },
{ "type": "Feature", "properties": { "strassenschluessel": "05974000004808187", "bezeichnung": "Auf der Anwende" }, "geometry": { "type": "Point", "coordinates": [ 7.978153499997285, 51.604746416510658 ] } },
{ "type": "Feature", "properties": { "strassenschluessel": "05974000004808196", "bezeichnung": "Bergstraßer Weg" }, "geometry": { "type": "Point", "coordinates": [ 8.001338686957032, 51.573675060702769 ] } },
{ "type": "Feature", "properties": { "strassenschluessel": "05974000004808197", "bezeichnung": "Lindweg" }, "geometry": { "type": "Point", "coordinates": [ 8.005911673768347, 51.57092216305545 ] } },
{ "type": "Feature", "properties": { "strassenschluessel": "05974000004808198", "bezeichnung": "Merklingser Weg" }, "geometry": { "type": "Point", "coordinates": [ 8.008017557561386, 51.567189728701912 ] } },
{ "type": "Feature", "properties": { "strassenschluessel": "05974000004808199", "bezeichnung": "Im Südfeld" }, "geometry": { "type": "Point", "coordinates": [ 8.002490202372933, 51.570298386812361 ] } },
{ "type": "Feature", "properties": { "strassenschluessel": "05974000004808200", "bezeichnung": "Im Dorfe" }, "geometry": { "type": "Point", "coordinates": [ 8.004996437428249, 51.572602973275139 ] } },
{ "type": "Feature", "properties": { "strassenschluessel": "05974000004808206", "bezeichnung": "Berksen" }, "geometry": { "type": "Point", "coordinates": [ 8.00226342797526, 51.643541121988264 ] } },
{ "type": "Feature", "properties": { "strassenschluessel": "05974000004808207", "bezeichnung": "Brunnenstraße" }, "geometry": { "type": "Point", "coordinates": [ 7.999101183384891, 51.635123883099212 ] } },
{ "type": "Feature", "properties": { "strassenschluessel": "05974000004808208", "bezeichnung": "Hacheney" }, "geometry": { "type": "Point", "coordinates": [ 8.026403712133645, 51.633906692935028 ] } },
{ "type": "Feature", "properties": { "strassenschluessel": "05974000004808209", "bezeichnung": "Hündlingsen" }, "geometry": { "type": "Point", "coordinates": [ 7.996066976452623, 51.648272091907593 ] } },
{ "type": "Feature", "properties": { "strassenschluessel": "05974000004808210", "bezeichnung": "In Nateln" }, "geometry": { "type": "Point", "coordinates": [ 8.003721826762035, 51.634399746047173 ] } },
{ "type": "Feature", "properties": { "strassenschluessel": "05974000004808211", "bezeichnung": "Haus Nateln" }, "geometry": { "type": "Point", "coordinates": [ 8.005724788034881, 51.632427946509608 ] } },
{ "type": "Feature", "properties": { "strassenschluessel": "05974000004808216", "bezeichnung": "Im Loh" }, "geometry": { "type": "Point", "coordinates": [ 7.987443048373856, 51.630883714272365 ] } },
{ "type": "Feature", "properties": { "strassenschluessel": "05974000004808217", "bezeichnung": "Nehlerheide" }, "geometry": { "type": "Point", "coordinates": [ 8.012742238090068, 51.61408417673956 ] } },
{ "type": "Feature", "properties": { "strassenschluessel": "05974000004808218", "bezeichnung": "Recklingser Straße" }, "geometry": { "type": "Point", "coordinates": [ 7.997334085944233, 51.623267124597319 ] } },
{ "type": "Feature", "properties": { "strassenschluessel": "05974000004808219", "bezeichnung": "Westen" }, "geometry": { "type": "Point", "coordinates": [ 8.009160816283599, 51.628740235907237 ] } },
{ "type": "Feature", "properties": { "strassenschluessel": "05974000004808220", "bezeichnung": "Elisabeth-Dreckmann-Weg" }, "geometry": null },
{ "type": "Feature", "properties": { "strassenschluessel": "05974000004808226", "bezeichnung": "Am Zollbaum" }, "geometry": { "type": "Point", "coordinates": [ 7.935559942841011, 51.600397856530556 ] } },
{ "type": "Feature", "properties": { "strassenschluessel": "05974000004808227", "bezeichnung": "Aulflucht" }, "geometry": { "type": "Point", "coordinates": [ 7.933292624413028, 51.604801534905803 ] } },
{ "type": "Feature", "properties": { "strassenschluessel": "05974000004808228", "bezeichnung": "Dreischerweg" }, "geometry": { "type": "Point", "coordinates": [ 7.929453083182057, 51.599173611763156 ] } },
{ "type": "Feature", "properties": { "strassenschluessel": "05974000004808229", "bezeichnung": "Delkenstraße" }, "geometry": { "type": "Point", "coordinates": [ 7.928611945026057, 51.598691118361316 ] } },
{ "type": "Feature", "properties": { "strassenschluessel": "05974000004808230", "bezeichnung": "Grosse Breite" }, "geometry": { "type": "Point", "coordinates": [ 7.926972724115776, 51.596637888982471 ] } },
{ "type": "Feature", "properties": { "strassenschluessel": "05974000004808231", "bezeichnung": "Hahnenkopf" }, "geometry": { "type": "Point", "coordinates": [ 7.931994272786741, 51.59677945939525 ] } },
{ "type": "Feature", "properties": { "strassenschluessel": "05974000004808232", "bezeichnung": "Heckenbrei" }, "geometry": { "type": "Point", "coordinates": [ 7.932964456057739, 51.599112607197561 ] } },
{ "type": "Feature", "properties": { "strassenschluessel": "05974000004808233", "bezeichnung": "Hudeweg" }, "geometry": { "type": "Point", "coordinates": [ 7.9132885590897, 51.59536633245672 ] } },
{ "type": "Feature", "properties": { "strassenschluessel": "05974000004808234", "bezeichnung": "Lindacker" }, "geometry": { "type": "Point", "coordinates": [ 7.928575018892612, 51.601586542803126 ] } },
{ "type": "Feature", "properties": { "strassenschluessel": "05974000004808235", "bezeichnung": "Lülfstraße" }, "geometry": { "type": "Point", "coordinates": [ 7.93288194700621, 51.599905700609241 ] } },
{ "type": "Feature", "properties": { "strassenschluessel": "05974000004808236", "bezeichnung": "Neustadtstraße" }, "geometry": { "type": "Point", "coordinates": [ 7.929564053031842, 51.602166139860977 ] } },
{ "type": "Feature", "properties": { "strassenschluessel": "05974000004808237", "bezeichnung": "Reekstraße" }, "geometry": { "type": "Point", "coordinates": [ 7.934385860056277, 51.60161915176316 ] } },
{ "type": "Feature", "properties": { "strassenschluessel": "05974000004808238", "bezeichnung": "Sauerbrei" }, "geometry": { "type": "Point", "coordinates": [ 7.932178724388717, 51.597764630196757 ] } },
{ "type": "Feature", "properties": { "strassenschluessel": "05974000004808239", "bezeichnung": "Schanze" }, "geometry": { "type": "Point", "coordinates": [ 7.928914875317369, 51.600128446776758 ] } },
{ "type": "Feature", "properties": { "strassenschluessel": "05974000004808240", "bezeichnung": "Schatterweg" }, "geometry": { "type": "Point", "coordinates": [ 7.932520521338262, 51.603475652939196 ] } },
{ "type": "Feature", "properties": { "strassenschluessel": "05974000004808241", "bezeichnung": "Scheidinger Straße" }, "geometry": { "type": "Point", "coordinates": [ 7.928927901223734, 51.599377793311412 ] } },
{ "type": "Feature", "properties": { "strassenschluessel": "05974000004808242", "bezeichnung": "Schützenstraße" }, "geometry": { "type": "Point", "coordinates": [ 7.932508454722398, 51.59800257951288 ] } },
{ "type": "Feature", "properties": { "strassenschluessel": "05974000004808243", "bezeichnung": "Kaltenhagen" }, "geometry": { "type": "Point", "coordinates": [ 7.923839644648379, 51.601524809520804 ] } },
{ "type": "Feature", "properties": { "strassenschluessel": "05974000004808244", "bezeichnung": "Wambeler Straße" }, "geometry": { "type": "Point", "coordinates": [ 7.927053519090181, 51.601441543067089 ] } },
{ "type": "Feature", "properties": { "strassenschluessel": "05974000004808245", "bezeichnung": "Sauerfeld" }, "geometry": { "type": "Point", "coordinates": [ 7.925681666312417, 51.590140433848688 ] } },
{ "type": "Feature", "properties": { "strassenschluessel": "05974000004808246", "bezeichnung": "Aulswinkel" }, "geometry": { "type": "Point", "coordinates": [ 7.935765088110939, 51.604338430670921 ] } },
{ "type": "Feature", "properties": { "strassenschluessel": "05974000004808247", "bezeichnung": "Am Bierbäumchen" }, "geometry": { "type": "Point", "coordinates": [ 7.92979938497483, 51.607667296242582 ] } },
{ "type": "Feature", "properties": { "strassenschluessel": "05974000004808248", "bezeichnung": "Oberster Dreisch" }, "geometry": { "type": "Point", "coordinates": [ 7.926590799654582, 51.598627090954189 ] } },
{ "type": "Feature", "properties": { "strassenschluessel": "05974000004808249", "bezeichnung": "Waldweg" }, "geometry": { "type": "Point", "coordinates": [ 7.925995734666528, 51.593828054284344 ] } },
{ "type": "Feature", "properties": { "strassenschluessel": "05974000004808250", "bezeichnung": "Am Landwehrbach" }, "geometry": { "type": "Point", "coordinates": [ 7.929683662344399, 51.598526460993973 ] } },
{ "type": "Feature", "properties": { "strassenschluessel": "05974000004808251", "bezeichnung": "Auf der Sauerbrei" }, "geometry": { "type": "Point", "coordinates": [ 7.931668267864256, 51.598635844535899 ] } },
{ "type": "Feature", "properties": { "strassenschluessel": "05974000004808252", "bezeichnung": "Schürmannweg" }, "geometry": { "type": "Point", "coordinates": [ 7.927221238186327, 51.595132419283381 ] } },
{ "type": "Feature", "properties": { "strassenschluessel": "05974000004808271", "bezeichnung": "Am Hügel" }, "geometry": { "type": "Point", "coordinates": [ 8.029780125440311, 51.57739210836079 ] } },
{ "type": "Feature", "properties": { "strassenschluessel": "05974000004808272", "bezeichnung": "Am Krausen Garten" }, "geometry": { "type": "Point", "coordinates": [ 8.029234626334599, 51.574272334615991 ] } },
{ "type": "Feature", "properties": { "strassenschluessel": "05974000004808273", "bezeichnung": "Bachstraße" }, "geometry": { "type": "Point", "coordinates": [ 8.036284585915405, 51.575946462283035 ] } },
{ "type": "Feature", "properties": { "strassenschluessel": "05974000004808274", "bezeichnung": "Baukeweg" }, "geometry": { "type": "Point", "coordinates": [ 8.036200746403694, 51.575115929366568 ] } },
{ "type": "Feature", "properties": { "strassenschluessel": "05974000004808275", "bezeichnung": "Buddemühle" }, "geometry": { "type": "Point", "coordinates": [ 8.040914549751896, 51.589301625164033 ] } },
{ "type": "Feature", "properties": { "strassenschluessel": "05974000004808276", "bezeichnung": "Denninghofweg" }, "geometry": { "type": "Point", "coordinates": [ 8.030685820247683, 51.580996674808105 ] } },
{ "type": "Feature", "properties": { "strassenschluessel": "05974000004808277", "bezeichnung": "Hoher Weg" }, "geometry": { "type": "Point", "coordinates": [ 8.032309881270503, 51.579349003711634 ] } },
{ "type": "Feature", "properties": { "strassenschluessel": "05974000004808278", "bezeichnung": "Kirchbreite" }, "geometry": { "type": "Point", "coordinates": [ 8.03365421904579, 51.579786493925049 ] } },
{ "type": "Feature", "properties": { "strassenschluessel": "05974000004808279", "bezeichnung": "Neppelmühle" }, "geometry": { "type": "Point", "coordinates": [ 8.045670717104816, 51.589151050225652 ] } },
{ "type": "Feature", "properties": { "strassenschluessel": "05974000004808280", "bezeichnung": "Ölmühlenweg" }, "geometry": { "type": "Point", "coordinates": [ 8.039914872492355, 51.573536929948823 ] } },
{ "type": "Feature", "properties": { "strassenschluessel": "05974000004808281", "bezeichnung": "Paradieser Weg" }, "geometry": { "type": "Point", "coordinates": [ 8.041960195876808, 51.572947050808956 ] } },
{ "type": "Feature", "properties": { "strassenschluessel": "05974000004808282", "bezeichnung": "Sägemühlenweg" }, "geometry": { "type": "Point", "coordinates": [ 8.036033234647439, 51.584027516483623 ] } },
{ "type": "Feature", "properties": { "strassenschluessel": "05974000004808283", "bezeichnung": "Schwefer Straße" }, "geometry": { "type": "Point", "coordinates": [ 8.035434457794606, 51.583456261070282 ] } },
{ "type": "Feature", "properties": { "strassenschluessel": "05974000004808284", "bezeichnung": "Soestweg" }, "geometry": { "type": "Point", "coordinates": [ 8.031676517563374, 51.582238702282538 ] } },
{ "type": "Feature", "properties": { "strassenschluessel": "05974000004808285", "bezeichnung": "Wohlmeine" }, "geometry": { "type": "Point", "coordinates": [ 8.037826290102773, 51.574849223801564 ] } },
{ "type": "Feature", "properties": { "strassenschluessel": "05974000004808286", "bezeichnung": "Zum Spielplatz" }, "geometry": { "type": "Point", "coordinates": [ 8.036776111653779, 51.577355238647613 ] } },
{ "type": "Feature", "properties": { "strassenschluessel": "05974000004808287", "bezeichnung": "Zum Vulting" }, "geometry": { "type": "Point", "coordinates": [ 8.034815268431915, 51.577303871958129 ] } },
{ "type": "Feature", "properties": { "strassenschluessel": "05974000004808288", "bezeichnung": "Zur Rotbuche" }, "geometry": { "type": "Point", "coordinates": [ 8.032856474670941, 51.578917698943954 ] } },
{ "type": "Feature", "properties": { "strassenschluessel": "05974000004808289", "bezeichnung": "Loershof" }, "geometry": { "type": "Point", "coordinates": [ 8.034647117827879, 51.581461204376964 ] } },
{ "type": "Feature", "properties": { "strassenschluessel": "05974000004808316", "bezeichnung": "Auf dem Felde" }, "geometry": { "type": "Point", "coordinates": [ 8.04995611093179, 51.6243204410708 ] } },
{ "type": "Feature", "properties": { "strassenschluessel": "05974000004808317", "bezeichnung": "Bruchstraße" }, "geometry": { "type": "Point", "coordinates": [ 8.049453729254662, 51.627880973507438 ] } },
{ "type": "Feature", "properties": { "strassenschluessel": "05974000004808318", "bezeichnung": "In der Helle" }, "geometry": { "type": "Point", "coordinates": [ 8.052283121597519, 51.629373269249243 ] } },
{ "type": "Feature", "properties": { "strassenschluessel": "05974000004808319", "bezeichnung": "Im Kloster" }, "geometry": { "type": "Point", "coordinates": [ 8.049082504515457, 51.624387740155086 ] } },
{ "type": "Feature", "properties": { "strassenschluessel": "05974000004808320", "bezeichnung": "Ringstraße" }, "geometry": { "type": "Point", "coordinates": [ 8.048746743958416, 51.627036725117073 ] } },
{ "type": "Feature", "properties": { "strassenschluessel": "05974000004808321", "bezeichnung": "Stocklarner Straße" }, "geometry": { "type": "Point", "coordinates": [ 8.049263048134986, 51.625070952935602 ] } },
{ "type": "Feature", "properties": { "strassenschluessel": "05974000004808331", "bezeichnung": "Am Tempel" }, "geometry": { "type": "Point", "coordinates": [ 7.988442702332411, 51.662702458845352 ] } },
{ "type": "Feature", "properties": { "strassenschluessel": "05974000004808332", "bezeichnung": "Auf der Koppel" }, "geometry": { "type": "Point", "coordinates": [ 7.966808702745841, 51.663903456755605 ] } },
{ "type": "Feature", "properties": { "strassenschluessel": "05974000004808333", "bezeichnung": "Ballhornweg" }, "geometry": { "type": "Point", "coordinates": [ 7.972653266919945, 51.668935295784941 ] } },
{ "type": "Feature", "properties": { "strassenschluessel": "05974000004808334", "bezeichnung": "Brauckstraße" }, "geometry": { "type": "Point", "coordinates": [ 7.982206683166667, 51.663290695951616 ] } },
{ "type": "Feature", "properties": { "strassenschluessel": "05974000004808335", "bezeichnung": "Eilmser Straße" }, "geometry": { "type": "Point", "coordinates": [ 7.970320657758043, 51.663622202786925 ] } },
{ "type": "Feature", "properties": { "strassenschluessel": "05974000004808336", "bezeichnung": "Eilmser Wald" }, "geometry": { "type": "Point", "coordinates": [ 7.9607719904829, 51.666782749471871 ] } },
{ "type": "Feature", "properties": { "strassenschluessel": "05974000004808337", "bezeichnung": "Dornenkamp" }, "geometry": { "type": "Point", "coordinates": [ 7.975725617835457, 51.665528826396681 ] } },
{ "type": "Feature", "properties": { "strassenschluessel": "05974000004808338", "bezeichnung": "Hesselnkamp" }, "geometry": { "type": "Point", "coordinates": [ 7.978352822287182, 51.669168048584488 ] } },
{ "type": "Feature", "properties": { "strassenschluessel": "05974000004808339", "bezeichnung": "Kanalstraße" }, "geometry": { "type": "Point", "coordinates": [ 7.988757681636493, 51.669635101619996 ] } },
{ "type": "Feature", "properties": { "strassenschluessel": "05974000004808340", "bezeichnung": "Kleiloh" }, "geometry": { "type": "Point", "coordinates": [ 7.992186685414254, 51.655813755336922 ] } },
{ "type": "Feature", "properties": { "strassenschluessel": "05974000004808341", "bezeichnung": "Köhner Weg" }, "geometry": { "type": "Point", "coordinates": [ 7.990770097072464, 51.670383964685485 ] } },
{ "type": "Feature", "properties": { "strassenschluessel": "05974000004808342", "bezeichnung": "Koppelstraße" }, "geometry": { "type": "Point", "coordinates": [ 7.969241300406397, 51.663362753490347 ] } },
{ "type": "Feature", "properties": { "strassenschluessel": "05974000004808343", "bezeichnung": "Postweg" }, "geometry": { "type": "Point", "coordinates": [ 7.988666714905226, 51.671889899075914 ] } },
{ "type": "Feature", "properties": { "strassenschluessel": "05974000004808344", "bezeichnung": "Schulstraße" }, "geometry": { "type": "Point", "coordinates": [ 7.981010429647753, 51.665301634992872 ] } },
{ "type": "Feature", "properties": { "strassenschluessel": "05974000004808345", "bezeichnung": "Vellinghauser Straße" }, "geometry": { "type": "Point", "coordinates": [ 7.982614891256317, 51.66464793041326 ] } },
{ "type": "Feature", "properties": { "strassenschluessel": "05974000004808346", "bezeichnung": "Westholz" }, "geometry": { "type": "Point", "coordinates": [ 7.983481637118782, 51.669092050390105 ] } },
{ "type": "Feature", "properties": { "strassenschluessel": "05974000004808347", "bezeichnung": "Schmielenkamp" }, "geometry": { "type": "Point", "coordinates": [ 7.983390623138501, 51.66420768325878 ] } },
{ "type": "Feature", "properties": { "strassenschluessel": "05974000004808348", "bezeichnung": "Talweg" }, "geometry": { "type": "Point", "coordinates": [ 7.982032623866022, 51.662740552583159 ] } },
{ "type": "Feature", "properties": { "strassenschluessel": "05974000004808349", "bezeichnung": "Gertönisplatz" }, "geometry": { "type": "Point", "coordinates": [ 7.995522414989731, 51.671299702765715 ] } },
{ "type": "Feature", "properties": { "strassenschluessel": "05974000004808350", "bezeichnung": "Burg Vellinghausen" }, "geometry": { "type": "Point", "coordinates": [ 7.989475956613501, 51.664172682608331 ] } },
{ "type": "Feature", "properties": { "strassenschluessel": "05974000004808371", "bezeichnung": "Ahornstraße" }, "geometry": { "type": "Point", "coordinates": [ 7.951957682607015, 51.621458569126432 ] } },
{ "type": "Feature", "properties": { "strassenschluessel": "05974000004808372", "bezeichnung": "Am Hachenbruch" }, "geometry": { "type": "Point", "coordinates": [ 7.964051912254769, 51.612700092613053 ] } },
{ "type": "Feature", "properties": { "strassenschluessel": "05974000004808373", "bezeichnung": "Am Harbruch" }, "geometry": { "type": "Point", "coordinates": [ 7.983014217946983, 51.627116327185263 ] } },
{ "type": "Feature", "properties": { "strassenschluessel": "05974000004808374", "bezeichnung": "Am Hundeteich" }, "geometry": { "type": "Point", "coordinates": [ 7.961761747204093, 51.623739669368007 ] } },
{ "type": "Feature", "properties": { "strassenschluessel": "05974000004808375", "bezeichnung": "Am Sportplatz" }, "geometry": { "type": "Point", "coordinates": [ 7.956056864226038, 51.62304627038327 ] } },
{ "type": "Feature", "properties": { "strassenschluessel": "05974000004808376", "bezeichnung": "Auf'm Kreiter" }, "geometry": { "type": "Point", "coordinates": [ 7.958908679979755, 51.619555534721194 ] } },
{ "type": "Feature", "properties": { "strassenschluessel": "05974000004808377", "bezeichnung": "Auf'm Tigge" }, "geometry": { "type": "Point", "coordinates": [ 7.94969223232814, 51.608366707138245 ] } },
{ "type": "Feature", "properties": { "strassenschluessel": "05974000004808378", "bezeichnung": "Bahnhofstraße" }, "geometry": { "type": "Point", "coordinates": [ 7.957923505352681, 51.619757348248122 ] } },
{ "type": "Feature", "properties": { "strassenschluessel": "05974000004808379", "bezeichnung": "Beckumer Straße" }, "geometry": { "type": "Point", "coordinates": [ 7.969738947939383, 51.62491318984479 ] } },
{ "type": "Feature", "properties": { "strassenschluessel": "05974000004808380", "bezeichnung": "Birkenstraße" }, "geometry": { "type": "Point", "coordinates": [ 7.955574269389707, 51.620367675916839 ] } },
{ "type": "Feature", "properties": { "strassenschluessel": "05974000004808381", "bezeichnung": "Boltenbreite" }, "geometry": { "type": "Point", "coordinates": [ 7.960237056202907, 51.619999636524504 ] } },
{ "type": "Feature", "properties": { "strassenschluessel": "05974000004808382", "bezeichnung": "Buchenstraße" }, "geometry": { "type": "Point", "coordinates": [ 7.957438826572645, 51.626966778895643 ] } },
{ "type": "Feature", "properties": { "strassenschluessel": "05974000004808383", "bezeichnung": "Dorfstraße" }, "geometry": { "type": "Point", "coordinates": [ 7.966738163864397, 51.623795224363484 ] } },
{ "type": "Feature", "properties": { "strassenschluessel": "05974000004808384", "bezeichnung": "Drosselweg" }, "geometry": { "type": "Point", "coordinates": [ 7.95798685276469, 51.617752225827402 ] } },
{ "type": "Feature", "properties": { "strassenschluessel": "05974000004808385", "bezeichnung": "Eichenstraße" }, "geometry": { "type": "Point", "coordinates": [ 7.957248277827733, 51.622230018898861 ] } },
{ "type": "Feature", "properties": { "strassenschluessel": "05974000004808386", "bezeichnung": "Erlenstraße" }, "geometry": { "type": "Point", "coordinates": [ 7.954561374043552, 51.619791155958737 ] } },
{ "type": "Feature", "properties": { "strassenschluessel": "05974000004808387", "bezeichnung": "Fasanenweg" }, "geometry": { "type": "Point", "coordinates": [ 7.950927234677087, 51.607019603977683 ] } },
{ "type": "Feature", "properties": { "strassenschluessel": "05974000004808388", "bezeichnung": "Finkenweg" }, "geometry": { "type": "Point", "coordinates": [ 7.960699399843182, 51.619734081790931 ] } },
{ "type": "Feature", "properties": { "strassenschluessel": "05974000004808389", "bezeichnung": "Frankenkamp" }, "geometry": { "type": "Point", "coordinates": [ 7.958708719280427, 51.613180608528751 ] } },
{ "type": "Feature", "properties": { "strassenschluessel": "05974000004808390", "bezeichnung": "Gartenstraße" }, "geometry": { "type": "Point", "coordinates": [ 7.953674259890002, 51.618683977017916 ] } },
{ "type": "Feature", "properties": { "strassenschluessel": "05974000004808391", "bezeichnung": "Grünstraße" }, "geometry": { "type": "Point", "coordinates": [ 7.95032609123224, 51.613131645896033 ] } },
{ "type": "Feature", "properties": { "strassenschluessel": "05974000004808392", "bezeichnung": "Hachenstraße" }, "geometry": { "type": "Point", "coordinates": [ 7.956823904946073, 51.613314102825385 ] } },
{ "type": "Feature", "properties": { "strassenschluessel": "05974000004808393", "bezeichnung": "Haselstraße" }, "geometry": { "type": "Point", "coordinates": [ 7.958226812501057, 51.621419239927064 ] } },
{ "type": "Feature", "properties": { "strassenschluessel": "05974000004808394", "bezeichnung": "Harkenbrei" }, "geometry": { "type": "Point", "coordinates": [ 7.953798124154076, 51.614266762810466 ] } },
{ "type": "Feature", "properties": { "strassenschluessel": "05974000004808395", "bezeichnung": "Heideweg" }, "geometry": { "type": "Point", "coordinates": [ 7.957538584958262, 51.610594414604321 ] } },
{ "type": "Feature", "properties": { "strassenschluessel": "05974000004808396", "bezeichnung": "Hermann-Löns-Straße" }, "geometry": { "type": "Point", "coordinates": [ 7.95181122368751, 51.620218944192956 ] } },
{ "type": "Feature", "properties": { "strassenschluessel": "05974000004808397", "bezeichnung": "Im Bruch" }, "geometry": { "type": "Point", "coordinates": [ 7.947606803257158, 51.61971610884008 ] } },
{ "type": "Feature", "properties": { "strassenschluessel": "05974000004808398", "bezeichnung": "Im Hagen" }, "geometry": { "type": "Point", "coordinates": [ 7.959949027267485, 51.621125925894425 ] } },
{ "type": "Feature", "properties": { "strassenschluessel": "05974000004808399", "bezeichnung": "Im Kreggenfeld" }, "geometry": { "type": "Point", "coordinates": [ 7.951191540292227, 51.612771306655745 ] } },
{ "type": "Feature", "properties": { "strassenschluessel": "05974000004808400", "bezeichnung": "Im Mühlenfeld" }, "geometry": { "type": "Point", "coordinates": [ 7.940226082043066, 51.620718717194109 ] } },
{ "type": "Feature", "properties": { "strassenschluessel": "05974000004808401", "bezeichnung": "In den Wulferten" }, "geometry": { "type": "Point", "coordinates": [ 7.946668210946612, 51.62228823752524 ] } },
{ "type": "Feature", "properties": { "strassenschluessel": "05974000004808402", "bezeichnung": "Kiefernstraße" }, "geometry": { "type": "Point", "coordinates": [ 7.954715893757263, 51.621077984522593 ] } },
{ "type": "Feature", "properties": { "strassenschluessel": "05974000004808403", "bezeichnung": "Kirchweg" }, "geometry": { "type": "Point", "coordinates": [ 7.967298872400844, 51.624683276166422 ] } },
{ "type": "Feature", "properties": { "strassenschluessel": "05974000004808404", "bezeichnung": "Klosterhof" }, "geometry": { "type": "Point", "coordinates": [ 7.964377747001311, 51.624841294847165 ] } },
{ "type": "Feature", "properties": { "strassenschluessel": "05974000004808405", "bezeichnung": "Kurzer Weg" }, "geometry": { "type": "Point", "coordinates": [ 7.959149400089215, 51.62140748779553 ] } },
{ "type": "Feature", "properties": { "strassenschluessel": "05974000004808406", "bezeichnung": "Ladestraße" }, "geometry": { "type": "Point", "coordinates": [ 7.95842638908818, 51.616564431543232 ] } },
{ "type": "Feature", "properties": { "strassenschluessel": "05974000004808407", "bezeichnung": "Landwehrkamp" }, "geometry": { "type": "Point", "coordinates": [ 7.949474578440742, 51.610735654700306 ] } },
{ "type": "Feature", "properties": { "strassenschluessel": "05974000004808408", "bezeichnung": "Lärchenweg" }, "geometry": { "type": "Point", "coordinates": [ 7.954447320693549, 51.619117817026329 ] } },
{ "type": "Feature", "properties": { "strassenschluessel": "05974000004808409", "bezeichnung": "Liethe" }, "geometry": { "type": "Point", "coordinates": [ 7.947242599873472, 51.618521418064979 ] } },
{ "type": "Feature", "properties": { "strassenschluessel": "05974000004808410", "bezeichnung": "Luisenstraße" }, "geometry": { "type": "Point", "coordinates": [ 7.954708881694073, 51.617467140609655 ] } },
{ "type": "Feature", "properties": { "strassenschluessel": "05974000004808411", "bezeichnung": "Ostbusch" }, "geometry": { "type": "Point", "coordinates": [ 7.960170728074898, 51.614911296957992 ] } },
{ "type": "Feature", "properties": { "strassenschluessel": "05974000004808412", "bezeichnung": "Pferdekamp" }, "geometry": { "type": "Point", "coordinates": [ 7.967584039786566, 51.615242273201183 ] } },
{ "type": "Feature", "properties": { "strassenschluessel": "05974000004808413", "bezeichnung": "Plass" }, "geometry": { "type": "Point", "coordinates": [ 7.94602059149579, 51.609138089311656 ] } },
{ "type": "Feature", "properties": { "strassenschluessel": "05974000004808414", "bezeichnung": "Rossbierke" }, "geometry": { "type": "Point", "coordinates": [ 7.953148813836829, 51.611618670030197 ] } },
{ "type": "Feature", "properties": { "strassenschluessel": "05974000004808415", "bezeichnung": "Schwarzer Weg" }, "geometry": { "type": "Point", "coordinates": [ 7.961520255533415, 51.615307366822478 ] } },
{ "type": "Feature", "properties": { "strassenschluessel": "05974000004808416", "bezeichnung": "Soestfeld" }, "geometry": { "type": "Point", "coordinates": [ 7.951268416035274, 51.60784754291425 ] } },
{ "type": "Feature", "properties": { "strassenschluessel": "05974000004808417", "bezeichnung": "Werler Straße" }, "geometry": { "type": "Point", "coordinates": [ 7.95379811457357, 51.615823142377835 ] } },
{ "type": "Feature", "properties": { "strassenschluessel": "05974000004808418", "bezeichnung": "Wolter-von-Plettenberg-Straße" }, "geometry": { "type": "Point", "coordinates": [ 7.954311819283447, 51.613171064453368 ] } },
{ "type": "Feature", "properties": { "strassenschluessel": "05974000004808419", "bezeichnung": "Zwischen den Hölzern" }, "geometry": { "type": "Point", "coordinates": [ 7.965277920535098, 51.612307960506158 ] } },
{ "type": "Feature", "properties": { "strassenschluessel": "05974000004808420", "bezeichnung": "Zur Königslaube" }, "geometry": { "type": "Point", "coordinates": [ 7.970563826506814, 51.61788550844939 ] } },
{ "type": "Feature", "properties": { "strassenschluessel": "05974000004808421", "bezeichnung": "Birkenhof" }, "geometry": { "type": "Point", "coordinates": [ 7.955554809145474, 51.621373829316312 ] } },
{ "type": "Feature", "properties": { "strassenschluessel": "05974000004808422", "bezeichnung": "Im Wiesengrund" }, "geometry": { "type": "Point", "coordinates": [ 7.95211776723325, 51.608258810210529 ] } },
{ "type": "Feature", "properties": { "strassenschluessel": "05974000004808423", "bezeichnung": "Am Elsternbusch" }, "geometry": { "type": "Point", "coordinates": [ 7.959525294739652, 51.61280976657028 ] } },
{ "type": "Feature", "properties": { "strassenschluessel": "05974000004808424", "bezeichnung": "Im Klostergarten" }, "geometry": { "type": "Point", "coordinates": [ 7.962574908741831, 51.623908989902731 ] } },
{ "type": "Feature", "properties": { "strassenschluessel": "05974000004808425", "bezeichnung": "Zur Grünen Aue" }, "geometry": { "type": "Point", "coordinates": [ 7.945478892073912, 51.621765778896794 ] } },
{ "type": "Feature", "properties": { "strassenschluessel": "05974000004808426", "bezeichnung": "Reiherstraße" }, "geometry": { "type": "Point", "coordinates": [ 7.961798685906362, 51.617360114113943 ] } },
{ "type": "Feature", "properties": { "strassenschluessel": "05974000004808427", "bezeichnung": "Starenschleife" }, "geometry": { "type": "Point", "coordinates": [ 7.959530889295835, 51.617181024966783 ] } },
{ "type": "Feature", "properties": { "strassenschluessel": "05974000004808428", "bezeichnung": "Sperberweg" }, "geometry": { "type": "Point", "coordinates": [ 7.96025033244127, 51.616544883736118 ] } },
{ "type": "Feature", "properties": { "strassenschluessel": "05974000004808429", "bezeichnung": "Sperlingsgasse" }, "geometry": { "type": "Point", "coordinates": [ 7.959668189237497, 51.61683577538173 ] } },
{ "type": "Feature", "properties": { "strassenschluessel": "05974000004808430", "bezeichnung": "Am Markt" }, "geometry": { "type": "Point", "coordinates": [ 7.955803579252013, 51.617169090015572 ] } },
{ "type": "Feature", "properties": { "strassenschluessel": "05974000004808431", "bezeichnung": "Lindenstraße" }, "geometry": { "type": "Point", "coordinates": [ 7.95200844059929, 51.617929688791108 ] } },
{ "type": "Feature", "properties": { "strassenschluessel": "05974000004808432", "bezeichnung": "Ulmenweg" }, "geometry": { "type": "Point", "coordinates": [ 7.95341240412997, 51.620957686977313 ] } },
{ "type": "Feature", "properties": { "strassenschluessel": "05974000004808433", "bezeichnung": "Weidestraße" }, "geometry": { "type": "Point", "coordinates": [ 7.964371436244197, 51.622014473097344 ] } },
{ "type": "Feature", "properties": { "strassenschluessel": "05974000004808434", "bezeichnung": "Im Haferkamp" }, "geometry": { "type": "Point", "coordinates": [ 7.961497136682969, 51.620780179661587 ] } },
{ "type": "Feature", "properties": { "strassenschluessel": "05974000004808435", "bezeichnung": "Im Weizenfeld" }, "geometry": { "type": "Point", "coordinates": [ 7.96217621959816, 51.621015378564685 ] } },
{ "type": "Feature", "properties": { "strassenschluessel": "05974000004808436", "bezeichnung": "Im Gerstenwinkel" }, "geometry": { "type": "Point", "coordinates": [ 7.962191123848255, 51.619904266967261 ] } },
{ "type": "Feature", "properties": { "strassenschluessel": "05974000004808437", "bezeichnung": "Im Maiswinkel" }, "geometry": { "type": "Point", "coordinates": [ 7.962737328831903, 51.618732470533644 ] } },
{ "type": "Feature", "properties": { "strassenschluessel": "05974000004808438", "bezeichnung": "Am Feldgraben" }, "geometry": { "type": "Point", "coordinates": [ 7.966010211882572, 51.619159852449336 ] } },
{ "type": "Feature", "properties": { "strassenschluessel": "05974000004808439", "bezeichnung": "Im Roggenkamp" }, "geometry": { "type": "Point", "coordinates": [ 7.961272157009318, 51.61865042272111 ] } },
{ "type": "Feature", "properties": { "strassenschluessel": "05974000004808440", "bezeichnung": "Smiths Aue" }, "geometry": { "type": "Point", "coordinates": [ 7.950105318141259, 51.613271806605781 ] } },
{ "type": "Feature", "properties": { "strassenschluessel": "05974000004808441", "bezeichnung": "Zur Lehmkuhle" }, "geometry": { "type": "Point", "coordinates": [ 7.952394890681695, 51.614858216806397 ] } },
{ "type": "Feature", "properties": { "strassenschluessel": "05974000004808442", "bezeichnung": "Brandenburger Straße" }, "geometry": { "type": "Point", "coordinates": [ 7.957226822656902, 51.615061021331606 ] } },
{ "type": "Feature", "properties": { "strassenschluessel": "05974000004808443", "bezeichnung": "Ketziner Straße" }, "geometry": { "type": "Point", "coordinates": [ 7.957688822835991, 51.615469795078297 ] } },
{ "type": "Feature", "properties": { "strassenschluessel": "05974000004808444", "bezeichnung": "Havelweg" }, "geometry": null },
{ "type": "Feature", "properties": { "strassenschluessel": "05974000004808445", "bezeichnung": "Dinkelstraße" }, "geometry": { "type": "Point", "coordinates": [ 7.964242935809672, 51.620257945417507 ] } },
{ "type": "Feature", "properties": { "strassenschluessel": "05974000004808446", "bezeichnung": "Adolph-Kolping-Straße" }, "geometry": { "type": "Point", "coordinates": [ 7.961376006808852, 51.618004735238415 ] } },
{ "type": "Feature", "properties": { "strassenschluessel": "05974000004808447", "bezeichnung": "Beerenkamp" }, "geometry": { "type": "Point", "coordinates": [ 7.963571953074633, 51.617405545330215 ] } },
{ "type": "Feature", "properties": { "strassenschluessel": "05974000004808448", "bezeichnung": "Kastanienweg" }, "geometry": { "type": "Point", "coordinates": [ 7.954553687857744, 51.620315449247322 ] } },
{ "type": "Feature", "properties": { "strassenschluessel": "05974000004808449", "bezeichnung": "Auf dem Bült" }, "geometry": { "type": "Point", "coordinates": [ 7.949088869488408, 51.611055326429344 ] } },
{ "type": "Feature", "properties": { "strassenschluessel": "05974000004808450", "bezeichnung": "Meyericher Kirchfeld" }, "geometry": { "type": "Point", "coordinates": [ 7.949453882743198, 51.6113112119316 ] } },
{ "type": "Feature", "properties": { "strassenschluessel": "05974000004808451", "bezeichnung": "Brink" }, "geometry": { "type": "Point", "coordinates": [ 7.950569473183432, 51.612004826059255 ] } },
{ "type": "Feature", "properties": { "strassenschluessel": "05974000004808452", "bezeichnung": "Alte Gärtnerei" }, "geometry": { "type": "Point", "coordinates": [ 7.952755161850936, 51.617846783923547 ] } },
{ "type": "Feature", "properties": { "strassenschluessel": "05974000004891694", "bezeichnung": "Balksen" }, "geometry": null },
{ "type": "Feature", "properties": { "strassenschluessel": "05974000004891695", "bezeichnung": "Berwicke" }, "geometry": { "type": "Point", "coordinates": [ 8.03453196772745, 51.620744813813779 ] } },
{ "type": "Feature", "properties": { "strassenschluessel": "05974000004891696", "bezeichnung": "Blumroth" }, "geometry": { "type": "Point", "coordinates": [ 8.06433304933411, 51.614483850728703 ] } },
{ "type": "Feature", "properties": { "strassenschluessel": "05974000004891697", "bezeichnung": "Borgeln" }, "geometry": { "type": "Point", "coordinates": [ 8.02850903021611, 51.595049125446174 ] } },
{ "type": "Feature", "properties": { "strassenschluessel": "05974000004891699", "bezeichnung": "Dinker" }, "geometry": { "type": "Point", "coordinates": [ 7.948855765796031, 51.641287910779319 ] } },
{ "type": "Feature", "properties": { "strassenschluessel": "05974000004891700", "bezeichnung": "Eilmsen" }, "geometry": null },
{ "type": "Feature", "properties": { "strassenschluessel": "05974000004891704", "bezeichnung": "Nateln" }, "geometry": null },
{ "type": "Feature", "properties": { "strassenschluessel": "05974000004891705", "bezeichnung": "Stocklarn" }, "geometry": null },
{ "type": "Feature", "properties": { "strassenschluessel": "05974000004891707", "bezeichnung": "Vellinghausen" }, "geometry": null },
{ "type": "Feature", "properties": { "strassenschluessel": "05974000004891708", "bezeichnung": "Dorfwelver" }, "geometry": null },
{ "type": "Feature", "properties": { "strassenschluessel": "05974000004891769", "bezeichnung": "Ehningsen" }, "geometry": null },
{ "type": "Feature", "properties": { "strassenschluessel": "05974000004891770", "bezeichnung": "Einecke" }, "geometry": null },
{ "type": "Feature", "properties": { "strassenschluessel": "05974000004891771", "bezeichnung": "Eineckerholsen" }, "geometry": null },
{ "type": "Feature", "properties": { "strassenschluessel": "05974000004891774", "bezeichnung": "Flerke" }, "geometry": { "type": "Point", "coordinates": [ 7.947521704534851, 51.59042634429295 ] } },
{ "type": "Feature", "properties": { "strassenschluessel": "05974000004891776", "bezeichnung": "Klotingen" }, "geometry": null },
{ "type": "Feature", "properties": { "strassenschluessel": "05974000004891778", "bezeichnung": "Merklingsen" }, "geometry": null },
{ "type": "Feature", "properties": { "strassenschluessel": "05974000004891779", "bezeichnung": "Meyerich" }, "geometry": null },
{ "type": "Feature", "properties": { "strassenschluessel": "05974000004891781", "bezeichnung": "Recklingsen" }, "geometry": null },
{ "type": "Feature", "properties": { "strassenschluessel": "05974000004891783", "bezeichnung": "Schwefe" }, "geometry": null },
{ "type": "Feature", "properties": { "strassenschluessel": "05974000004891784", "bezeichnung": "Kirchwelver" }, "geometry": null },
{ "type": "Feature", "properties": { "strassenschluessel": "05974000004891928", "bezeichnung": "Scheidingen" }, "geometry": null },
{ "type": "Feature", "properties": { "strassenschluessel": "05974000004891929", "bezeichnung": "Illingen" }, "geometry": null }
]
}
